{
  "top": {
    "Ahri": {
      "wr": 51.47,
      "pr": 0.13,
      "br": 5.28,
      "avgWr": 50.0
    },
    "Akshan": {
      "wr": 49.15,
      "pr": 0.13,
      "br": 1.83,
      "avgWr": 50.0
    },
    "Akali": {
      "wr": 49.24,
      "pr": 2.59,
      "br": 17.85,
      "avgWr": 50.0
    },
    "Aatrox": {
      "wr": 49.15,
      "pr": 5.19,
      "br": 7.75,
      "avgWr": 50.0
    },
    "Ambessa": {
      "wr": 47.83,
      "pr": 2.66,
      "br": 7.17,
      "avgWr": 50.0
    },
    "Alistar": {
      "wr": 44.26,
      "pr": 0.11,
      "br": 1.21,
      "avgWr": 50.0
    },
    "Anivia": {
      "wr": 51.66,
      "pr": 0.7,
      "br": 2.55,
      "avgWr": 50.0
    },
    "Annie": {
      "wr": 51.62,
      "pr": 0.13,
      "br": 0.89,
      "avgWr": 50.0
    },
    "Aphelios": {
      "wr": 44.41,
      "pr": 0.03,
      "br": 2.23,
      "avgWr": 50.0
    },
    "Ashe": {
      "wr": 46.26,
      "pr": 0.22,
      "br": 7.56,
      "avgWr": 50.0
    },
    "Aurelion Sol": {
      "wr": 51.17,
      "pr": 0.17,
      "br": 1.31,
      "avgWr": 50.0
    },
    "Aurora": {
      "wr": 49.15,
      "pr": 0.61,
      "br": 2.16,
      "avgWr": 50.0
    },
    "Azir": {
      "wr": 49.86,
      "pr": 0.09,
      "br": 0.41,
      "avgWr": 50.0
    },
    "Bel'Veth": {
      "wr": 46.62,
      "pr": 0.03,
      "br": 1.49,
      "avgWr": 50.0
    },
    "Brand": {
      "wr": 50.93,
      "pr": 0.31,
      "br": 7.14,
      "avgWr": 50.0
    },
    "Briar": {
      "wr": 51.49,
      "pr": 0.32,
      "br": 14.78,
      "avgWr": 50.0
    },
    "Caitlyn": {
      "wr": 45.49,
      "pr": 0.26,
      "br": 30.31,
      "avgWr": 50.0
    },
    "Camille": {
      "wr": 49.0,
      "pr": 1.93,
      "br": 0.64,
      "avgWr": 50.0
    },
    "Cassiopeia": {
      "wr": 49.96,
      "pr": 0.38,
      "br": 0.94,
      "avgWr": 50.0
    },
    "Cho'Gath": {
      "wr": 49.6,
      "pr": 2.82,
      "br": 1.07,
      "avgWr": 50.0
    },
    "Corki": {
      "wr": 43.51,
      "pr": 0.05,
      "br": 0.43,
      "avgWr": 50.0
    },
    "Diana": {
      "wr": 49.06,
      "pr": 0.13,
      "br": 5.86,
      "avgWr": 50.0
    },
    "Darius": {
      "wr": 48.3,
      "pr": 8.36,
      "br": 16.97,
      "avgWr": 50.0
    },
    "Dr. Mundo": {
      "wr": 51.05,
      "pr": 3.82,
      "br": 8.64,
      "avgWr": 50.0
    },
    "Draven": {
      "wr": 46.3,
      "pr": 0.12,
      "br": 9.68,
      "avgWr": 50.0
    },
    "Ekko": {
      "wr": 47.08,
      "pr": 0.11,
      "br": 2.14,
      "avgWr": 50.0
    },
    "Elise": {
      "wr": 48.01,
      "pr": 0.09,
      "br": 0.86,
      "avgWr": 50.0
    },
    "Evelynn": {
      "wr": 45.03,
      "pr": 0.03,
      "br": 1.83,
      "avgWr": 50.0
    },
    "Ezreal": {
      "wr": 42.37,
      "pr": 0.17,
      "br": 7.18,
      "avgWr": 50.0
    },
    "Fiddlesticks": {
      "wr": 50.7,
      "pr": 0.36,
      "br": 1.16,
      "avgWr": 50.0
    },
    "Fizz": {
      "wr": 47.8,
      "pr": 0.11,
      "br": 9.87,
      "avgWr": 50.0
    },
    "Fiora": {
      "wr": 48.95,
      "pr": 2.93,
      "br": 3.14,
      "avgWr": 50.0
    },
    "Galio": {
      "wr": 48.2,
      "pr": 0.17,
      "br": 1.6,
      "avgWr": 50.0
    },
    "Gangplank": {
      "wr": 50.1,
      "pr": 3.43,
      "br": 2.72,
      "avgWr": 50.0
    },
    "Gnar": {
      "wr": 48.56,
      "pr": 3.28,
      "br": 1.04,
      "avgWr": 50.0
    },
    "Gragas": {
      "wr": 47.6,
      "pr": 1.54,
      "br": 0.42,
      "avgWr": 50.0
    },
    "Garen": {
      "wr": 52.04,
      "pr": 10.82,
      "br": 11.52,
      "avgWr": 50.0
    },
    "Graves": {
      "wr": 46.24,
      "pr": 0.22,
      "br": 10.4,
      "avgWr": 50.0
    },
    "Gwen": {
      "wr": 48.29,
      "pr": 2.39,
      "br": 2.69,
      "avgWr": 50.0
    },
    "Hecarim": {
      "wr": 34.37,
      "pr": 0.01,
      "br": 1.34,
      "avgWr": 50.0
    },
    "Heimerdinger": {
      "wr": 50.41,
      "pr": 1.91,
      "br": 4.49,
      "avgWr": 50.0
    },
    "Hwei": {
      "wr": 51.24,
      "pr": 0.06,
      "br": 1.51,
      "avgWr": 50.0
    },
    "Illaoi": {
      "wr": 51.03,
      "pr": 3.54,
      "br": 8.79,
      "avgWr": 50.0
    },
    "Irelia": {
      "wr": 50.23,
      "pr": 3.91,
      "br": 11.81,
      "avgWr": 50.0
    },
    "Ivern": {
      "wr": 46.79,
      "pr": 0.07,
      "br": 0.29,
      "avgWr": 50.0
    },
    "Janna": {
      "wr": 47.07,
      "pr": 0.02,
      "br": 0.38,
      "avgWr": 50.0
    },
    "Jarvan IV": {
      "wr": 45.57,
      "pr": 0.08,
      "br": 1.05,
      "avgWr": 50.0
    },
    "Jax": {
      "wr": 49.67,
      "pr": 5.46,
      "br": 10.21,
      "avgWr": 50.0
    },
    "Jayce": {
      "wr": 47.78,
      "pr": 2.96,
      "br": 2.4,
      "avgWr": 50.0
    },
    "Jhin": {
      "wr": 46.59,
      "pr": 0.16,
      "br": 3.63,
      "avgWr": 50.0
    },
    "K'Sante": {
      "wr": 46.02,
      "pr": 2.63,
      "br": 1.51,
      "avgWr": 50.0
    },
    "Kai'Sa": {
      "wr": 45.79,
      "pr": 0.15,
      "br": 2.2,
      "avgWr": 50.0
    },
    "Kalista": {
      "wr": 47.68,
      "pr": 0.12,
      "br": 0.33,
      "avgWr": 50.0
    },
    "Karma": {
      "wr": 48.46,
      "pr": 0.16,
      "br": 5.26,
      "avgWr": 50.0
    },
    "Karthus": {
      "wr": 47.04,
      "pr": 0.07,
      "br": 0.58,
      "avgWr": 50.0
    },
    "Kassadin": {
      "wr": 50.42,
      "pr": 0.07,
      "br": 1.47,
      "avgWr": 50.0
    },
    "Katarina": {
      "wr": 48.7,
      "pr": 0.08,
      "br": 7.83,
      "avgWr": 50.0
    },
    "Kayle": {
      "wr": 52.1,
      "pr": 3.66,
      "br": 3.54,
      "avgWr": 50.0
    },
    "Kayn": {
      "wr": 49.03,
      "pr": 0.52,
      "br": 5.33,
      "avgWr": 50.0
    },
    "Kennen": {
      "wr": 48.42,
      "pr": 1.78,
      "br": 1.39,
      "avgWr": 50.0
    },
    "Kindred": {
      "wr": 39.38,
      "pr": 0.02,
      "br": 0.95,
      "avgWr": 50.0
    },
    "Kled": {
      "wr": 51.52,
      "pr": 1.3,
      "br": 0.76,
      "avgWr": 50.0
    },
    "Kog'Maw": {
      "wr": 50.67,
      "pr": 0.07,
      "br": 0.45,
      "avgWr": 50.0
    },
    "LeBlanc": {
      "wr": 48.35,
      "pr": 0.07,
      "br": 12.67,
      "avgWr": 50.0
    },
    "Lee Sin": {
      "wr": 43.36,
      "pr": 0.19,
      "br": 11.06,
      "avgWr": 50.0
    },
    "Lillia": {
      "wr": 46.94,
      "pr": 0.1,
      "br": 2.14,
      "avgWr": 50.0
    },
    "Lissandra": {
      "wr": 51.75,
      "pr": 0.2,
      "br": 2.18,
      "avgWr": 50.0
    },
    "Lulu": {
      "wr": 43.59,
      "pr": 0.05,
      "br": 6.08,
      "avgWr": 50.0
    },
    "Lucian": {
      "wr": 42.46,
      "pr": 0.09,
      "br": 2.14,
      "avgWr": 50.0
    },
    "Malphite": {
      "wr": 51.25,
      "pr": 6.67,
      "br": 17.28,
      "avgWr": 50.0
    },
    "Maokai": {
      "wr": 50.04,
      "pr": 0.45,
      "br": 0.31,
      "avgWr": 50.0
    },
    "Malzahar": {
      "wr": 50.42,
      "pr": 0.67,
      "br": 16.67,
      "avgWr": 50.0
    },
    "Master Yi": {
      "wr": 47.09,
      "pr": 0.92,
      "br": 19.04,
      "avgWr": 50.0
    },
    "Mel": {
      "wr": 46.15,
      "pr": 0.12,
      "br": 39.41,
      "avgWr": 50.0
    },
    "Mordekaiser": {
      "wr": 51.34,
      "pr": 8.33,
      "br": 14.37,
      "avgWr": 50.0
    },
    "Morgana": {
      "wr": 49.74,
      "pr": 0.14,
      "br": 24.06,
      "avgWr": 50.0
    },
    "Naafiri": {
      "wr": 51.48,
      "pr": 0.43,
      "br": 19.43,
      "avgWr": 50.0
    },
    "Nasus": {
      "wr": 50.47,
      "pr": 4.64,
      "br": 5.23,
      "avgWr": 50.0
    },
    "Nautilus": {
      "wr": 46.89,
      "pr": 0.08,
      "br": 13.34,
      "avgWr": 50.0
    },
    "Neeko": {
      "wr": 48.85,
      "pr": 0.08,
      "br": 1.42,
      "avgWr": 50.0
    },
    "Nidalee": {
      "wr": 43.17,
      "pr": 0.07,
      "br": 0.51,
      "avgWr": 50.0
    },
    "Nilah": {
      "wr": 40.51,
      "pr": 0.01,
      "br": 2.47,
      "avgWr": 50.0
    },
    "Nocturne": {
      "wr": 49.91,
      "pr": 0.1,
      "br": 15.13,
      "avgWr": 50.0
    },
    "Nunu & Willump": {
      "wr": 36.26,
      "pr": 0.01,
      "br": 0.55,
      "avgWr": 50.0
    },
    "Olaf": {
      "wr": 50.72,
      "pr": 2.21,
      "br": 1.8,
      "avgWr": 50.0
    },
    "Orianna": {
      "wr": 48.88,
      "pr": 0.03,
      "br": 0.7,
      "avgWr": 50.0
    },
    "Ornn": {
      "wr": 51.51,
      "pr": 3.84,
      "br": 0.81,
      "avgWr": 50.0
    },
    "Pantheon": {
      "wr": 50.1,
      "pr": 1.73,
      "br": 2.24,
      "avgWr": 50.0
    },
    "Poppy": {
      "wr": 50.14,
      "pr": 0.89,
      "br": 1.5,
      "avgWr": 50.0
    },
    "Qiyana": {
      "wr": 50.13,
      "pr": 0.07,
      "br": 0.82,
      "avgWr": 50.0
    },
    "Rakan": {
      "wr": 44.7,
      "pr": 0.02,
      "br": 0.29,
      "avgWr": 50.0
    },
    "Quinn": {
      "wr": 49.16,
      "pr": 1.34,
      "br": 1.15,
      "avgWr": 50.0
    },
    "Rammus": {
      "wr": 46.89,
      "pr": 0.11,
      "br": 5.73,
      "avgWr": 50.0
    },
    "Rek'Sai": {
      "wr": 49.97,
      "pr": 0.11,
      "br": 0.79,
      "avgWr": 50.0
    },
    "Rell": {
      "wr": 44.51,
      "pr": 0.01,
      "br": 0.87,
      "avgWr": 50.0
    },
    "Renekton": {
      "wr": 49.73,
      "pr": 5.02,
      "br": 3.2,
      "avgWr": 50.0
    },
    "Rengar": {
      "wr": 45.9,
      "pr": 0.21,
      "br": 3.45,
      "avgWr": 50.0
    },
    "Riven": {
      "wr": 48.31,
      "pr": 2.56,
      "br": 1.14,
      "avgWr": 50.0
    },
    "Rumble": {
      "wr": 48.15,
      "pr": 1.94,
      "br": 0.88,
      "avgWr": 50.0
    },
    "Ryze": {
      "wr": 48.86,
      "pr": 0.57,
      "br": 0.63,
      "avgWr": 50.0
    },
    "Senna": {
      "wr": 48.26,
      "pr": 0.15,
      "br": 1.2,
      "avgWr": 50.0
    },
    "Sejuani": {
      "wr": 50.49,
      "pr": 0.23,
      "br": 0.23,
      "avgWr": 50.0
    },
    "Shaco": {
      "wr": 44.97,
      "pr": 0.26,
      "br": 26.81,
      "avgWr": 50.0
    },
    "Shen": {
      "wr": 50.78,
      "pr": 3.49,
      "br": 1.82,
      "avgWr": 50.0
    },
    "Shyvana": {
      "wr": 45.58,
      "pr": 0.44,
      "br": 9.55,
      "avgWr": 50.0
    },
    "Sett": {
      "wr": 51.59,
      "pr": 7.41,
      "br": 4.49,
      "avgWr": 50.0
    },
    "Singed": {
      "wr": 52.41,
      "pr": 2.15,
      "br": 0.91,
      "avgWr": 50.0
    },
    "Sion": {
      "wr": 51.3,
      "pr": 4.1,
      "br": 1.33,
      "avgWr": 50.0
    },
    "Skarner": {
      "wr": 45.59,
      "pr": 0.22,
      "br": 0.17,
      "avgWr": 50.0
    },
    "Smolder": {
      "wr": 46.74,
      "pr": 0.59,
      "br": 6.02,
      "avgWr": 50.0
    },
    "Soraka": {
      "wr": 46.05,
      "pr": 0.04,
      "br": 2.48,
      "avgWr": 50.0
    },
    "Swain": {
      "wr": 49.84,
      "pr": 0.57,
      "br": 5.83,
      "avgWr": 50.0
    },
    "Syndra": {
      "wr": 50.48,
      "pr": 0.05,
      "br": 2.27,
      "avgWr": 50.0
    },
    "Sylas": {
      "wr": 49.27,
      "pr": 0.9,
      "br": 11.12,
      "avgWr": 50.0
    },
    "Tahm Kench": {
      "wr": 49.85,
      "pr": 2.86,
      "br": 4.4,
      "avgWr": 50.0
    },
    "Taliyah": {
      "wr": 47.13,
      "pr": 0.02,
      "br": 0.19,
      "avgWr": 50.0
    },
    "Taric": {
      "wr": 40.55,
      "pr": 0.02,
      "br": 0.3,
      "avgWr": 50.0
    },
    "Talon": {
      "wr": 45.28,
      "pr": 0.06,
      "br": 2.58,
      "avgWr": 50.0
    },
    "Teemo": {
      "wr": 51.28,
      "pr": 5.94,
      "br": 13.01,
      "avgWr": 50.0
    },
    "Trundle": {
      "wr": 49.4,
      "pr": 1.84,
      "br": 0.7,
      "avgWr": 50.0
    },
    "Tristana": {
      "wr": 44.4,
      "pr": 0.11,
      "br": 2.38,
      "avgWr": 50.0
    },
    "Tryndamere": {
      "wr": 50.15,
      "pr": 3.57,
      "br": 2.78,
      "avgWr": 50.0
    },
    "Twisted Fate": {
      "wr": 47.37,
      "pr": 0.25,
      "br": 0.53,
      "avgWr": 50.0
    },
    "Udyr": {
      "wr": 47.74,
      "pr": 0.53,
      "br": 0.65,
      "avgWr": 50.0
    },
    "Twitch": {
      "wr": 41.93,
      "pr": 0.03,
      "br": 7.76,
      "avgWr": 50.0
    },
    "Urgot": {
      "wr": 51.24,
      "pr": 2.83,
      "br": 1.46,
      "avgWr": 50.0
    },
    "Varus": {
      "wr": 49.65,
      "pr": 1.48,
      "br": 2.51,
      "avgWr": 50.0
    },
    "Veigar": {
      "wr": 50.92,
      "pr": 0.23,
      "br": 4.05,
      "avgWr": 50.0
    },
    "Vayne": {
      "wr": 49.31,
      "pr": 4.05,
      "br": 11.96,
      "avgWr": 50.0
    },
    "Vel'Koz": {
      "wr": 51.97,
      "pr": 0.1,
      "br": 1.61,
      "avgWr": 50.0
    },
    "Vex": {
      "wr": 49.51,
      "pr": 0.04,
      "br": 4.19,
      "avgWr": 50.0
    },
    "Viego": {
      "wr": 46.71,
      "pr": 0.13,
      "br": 10.7,
      "avgWr": 50.0
    },
    "Vi": {
      "wr": 45.61,
      "pr": 0.16,
      "br": 1.17,
      "avgWr": 50.0
    },
    "Viktor": {
      "wr": 51.43,
      "pr": 0.12,
      "br": 2.98,
      "avgWr": 50.0
    },
    "Vladimir": {
      "wr": 49.55,
      "pr": 1.07,
      "br": 3.38,
      "avgWr": 50.0
    },
    "Warwick": {
      "wr": 50.98,
      "pr": 1.13,
      "br": 4.94,
      "avgWr": 50.0
    },
    "Volibear": {
      "wr": 50.19,
      "pr": 3.89,
      "br": 3.88,
      "avgWr": 50.0
    },
    "Xin Zhao": {
      "wr": 49.9,
      "pr": 0.73,
      "br": 2.65,
      "avgWr": 50.0
    },
    "Yasuo": {
      "wr": 48.6,
      "pr": 2.94,
      "br": 20.71,
      "avgWr": 50.0
    },
    "Yorick": {
      "wr": 51.62,
      "pr": 5.41,
      "br": 12.52,
      "avgWr": 50.0
    },
    "Yone": {
      "wr": 49.95,
      "pr": 5.63,
      "br": 7.01,
      "avgWr": 50.0
    },
    "Zaahen": {
      "wr": 49.2,
      "pr": 2.41,
      "br": 4.15,
      "avgWr": 50.0
    },
    "Zed": {
      "wr": 50.7,
      "pr": 0.32,
      "br": 22.89,
      "avgWr": 50.0
    },
    "Zeri": {
      "wr": 43.71,
      "pr": 0.02,
      "br": 0.21,
      "avgWr": 50.0
    },
    "Zac": {
      "wr": 51.48,
      "pr": 0.32,
      "br": 0.77,
      "avgWr": 50.0
    },
    "Ziggs": {
      "wr": 48.03,
      "pr": 0.05,
      "br": 0.76,
      "avgWr": 50.0
    },
    "Zilean": {
      "wr": 53.55,
      "pr": 0.08,
      "br": 0.8,
      "avgWr": 50.0
    },
    "Zoe": {
      "wr": 49.73,
      "pr": 0.1,
      "br": 3.48,
      "avgWr": 50.0
    },
    "Zyra": {
      "wr": 48.16,
      "pr": 0.05,
      "br": 4.19,
      "avgWr": 50.0
    }
  },
  "jungle": {
    "Aatrox": {
      "wr": 50.5,
      "pr": 0.94,
      "br": 7.75,
      "avgWr": 50.0
    },
    "Ambessa": {
      "wr": 48.9,
      "pr": 3.06,
      "br": 7.17,
      "avgWr": 50.0
    },
    "Amumu": {
      "wr": 52.03,
      "pr": 4.1,
      "br": 2.65,
      "avgWr": 50.0
    },
    "Aurelion Sol": {
      "wr": 45.68,
      "pr": 0.12,
      "br": 1.31,
      "avgWr": 50.0
    },
    "Bel'Veth": {
      "wr": 49.91,
      "pr": 1.37,
      "br": 1.49,
      "avgWr": 50.0
    },
    "Brand": {
      "wr": 50.22,
      "pr": 0.53,
      "br": 7.14,
      "avgWr": 50.0
    },
    "Briar": {
      "wr": 52.73,
      "pr": 6.32,
      "br": 14.78,
      "avgWr": 50.0
    },
    "Camille": {
      "wr": 45.2,
      "pr": 0.16,
      "br": 0.64,
      "avgWr": 50.0
    },
    "Cho'Gath": {
      "wr": 51.63,
      "pr": 0.52,
      "br": 1.07,
      "avgWr": 50.0
    },
    "Diana": {
      "wr": 49.47,
      "pr": 3.88,
      "br": 5.86,
      "avgWr": 50.0
    },
    "Darius": {
      "wr": 50.22,
      "pr": 0.76,
      "br": 16.97,
      "avgWr": 50.0
    },
    "Dr. Mundo": {
      "wr": 51.42,
      "pr": 2.64,
      "br": 8.64,
      "avgWr": 50.0
    },
    "Ekko": {
      "wr": 49.79,
      "pr": 3.32,
      "br": 2.14,
      "avgWr": 50.0
    },
    "Elise": {
      "wr": 50.01,
      "pr": 1.53,
      "br": 0.86,
      "avgWr": 50.0
    },
    "Evelynn": {
      "wr": 49.62,
      "pr": 2.23,
      "br": 1.83,
      "avgWr": 50.0
    },
    "Fiddlesticks": {
      "wr": 50.77,
      "pr": 2.36,
      "br": 1.16,
      "avgWr": 50.0
    },
    "Fizz": {
      "wr": 50.79,
      "pr": 0.89,
      "br": 9.87,
      "avgWr": 50.0
    },
    "Galio": {
      "wr": 41.45,
      "pr": 0.02,
      "br": 1.6,
      "avgWr": 50.0
    },
    "Gnar": {
      "wr": 42.93,
      "pr": 0.03,
      "br": 1.04,
      "avgWr": 50.0
    },
    "Gragas": {
      "wr": 47.73,
      "pr": 0.52,
      "br": 0.42,
      "avgWr": 50.0
    },
    "Garen": {
      "wr": 42.6,
      "pr": 0.23,
      "br": 11.52,
      "avgWr": 50.0
    },
    "Graves": {
      "wr": 50.0,
      "pr": 9.66,
      "br": 10.4,
      "avgWr": 50.0
    },
    "Gwen": {
      "wr": 49.43,
      "pr": 0.74,
      "br": 2.69,
      "avgWr": 50.0
    },
    "Hecarim": {
      "wr": 47.5,
      "pr": 2.49,
      "br": 1.34,
      "avgWr": 50.0
    },
    "Heimerdinger": {
      "wr": 43.24,
      "pr": 0.02,
      "br": 4.49,
      "avgWr": 50.0
    },
    "Ivern": {
      "wr": 49.23,
      "pr": 0.85,
      "br": 0.29,
      "avgWr": 50.0
    },
    "Jarvan IV": {
      "wr": 50.39,
      "pr": 5.14,
      "br": 1.05,
      "avgWr": 50.0
    },
    "Jax": {
      "wr": 50.37,
      "pr": 4.02,
      "br": 10.21,
      "avgWr": 50.0
    },
    "Jayce": {
      "wr": 48.74,
      "pr": 0.47,
      "br": 2.4,
      "avgWr": 50.0
    },
    "Kai'Sa": {
      "wr": 42.54,
      "pr": 0.07,
      "br": 2.2,
      "avgWr": 50.0
    },
    "Karthus": {
      "wr": 48.9,
      "pr": 1.27,
      "br": 0.58,
      "avgWr": 50.0
    },
    "Kayle": {
      "wr": 47.15,
      "pr": 0.03,
      "br": 3.54,
      "avgWr": 50.0
    },
    "Kayn": {
      "wr": 50.41,
      "pr": 8.17,
      "br": 5.33,
      "avgWr": 50.0
    },
    "Kha'Zix": {
      "wr": 47.97,
      "pr": 4.47,
      "br": 2.83,
      "avgWr": 50.0
    },
    "Kindred": {
      "wr": 48.26,
      "pr": 2.39,
      "br": 0.95,
      "avgWr": 50.0
    },
    "Kled": {
      "wr": 44.35,
      "pr": 0.01,
      "br": 0.76,
      "avgWr": 50.0
    },
    "Lee Sin": {
      "wr": 48.76,
      "pr": 10.51,
      "br": 11.06,
      "avgWr": 50.0
    },
    "Lillia": {
      "wr": 51.06,
      "pr": 3.36,
      "br": 2.14,
      "avgWr": 50.0
    },
    "Malphite": {
      "wr": 48.42,
      "pr": 1.74,
      "br": 17.28,
      "avgWr": 50.0
    },
    "Maokai": {
      "wr": 49.85,
      "pr": 0.36,
      "br": 0.31,
      "avgWr": 50.0
    },
    "Master Yi": {
      "wr": 50.05,
      "pr": 9.52,
      "br": 19.04,
      "avgWr": 50.0
    },
    "Mordekaiser": {
      "wr": 52.32,
      "pr": 0.62,
      "br": 14.37,
      "avgWr": 50.0
    },
    "Morgana": {
      "wr": 49.78,
      "pr": 0.36,
      "br": 24.06,
      "avgWr": 50.0
    },
    "Naafiri": {
      "wr": 50.99,
      "pr": 5.64,
      "br": 19.43,
      "avgWr": 50.0
    },
    "Nasus": {
      "wr": 51.75,
      "pr": 1.12,
      "br": 5.23,
      "avgWr": 50.0
    },
    "Nautilus": {
      "wr": 46.47,
      "pr": 0.11,
      "br": 13.34,
      "avgWr": 50.0
    },
    "Neeko": {
      "wr": 46.89,
      "pr": 0.08,
      "br": 1.42,
      "avgWr": 50.0
    },
    "Nidalee": {
      "wr": 46.84,
      "pr": 1.4,
      "br": 0.51,
      "avgWr": 50.0
    },
    "Nilah": {
      "wr": 40.5,
      "pr": 0.01,
      "br": 2.47,
      "avgWr": 50.0
    },
    "Nocturne": {
      "wr": 51.96,
      "pr": 9.27,
      "br": 15.13,
      "avgWr": 50.0
    },
    "Nunu & Willump": {
      "wr": 49.76,
      "pr": 2.04,
      "br": 0.55,
      "avgWr": 50.0
    },
    "Olaf": {
      "wr": 49.42,
      "pr": 0.31,
      "br": 1.8,
      "avgWr": 50.0
    },
    "Ornn": {
      "wr": 47.52,
      "pr": 0.04,
      "br": 0.81,
      "avgWr": 50.0
    },
    "Pantheon": {
      "wr": 48.53,
      "pr": 1.59,
      "br": 2.24,
      "avgWr": 50.0
    },
    "Poppy": {
      "wr": 48.72,
      "pr": 0.44,
      "br": 1.5,
      "avgWr": 50.0
    },
    "Qiyana": {
      "wr": 46.27,
      "pr": 0.64,
      "br": 0.82,
      "avgWr": 50.0
    },
    "Quinn": {
      "wr": 42.07,
      "pr": 0.06,
      "br": 1.15,
      "avgWr": 50.0
    },
    "Rammus": {
      "wr": 52.92,
      "pr": 2.58,
      "br": 5.73,
      "avgWr": 50.0
    },
    "Rek'Sai": {
      "wr": 50.29,
      "pr": 1.24,
      "br": 0.79,
      "avgWr": 50.0
    },
    "Rengar": {
      "wr": 46.07,
      "pr": 2.99,
      "br": 3.45,
      "avgWr": 50.0
    },
    "Riven": {
      "wr": 44.43,
      "pr": 0.12,
      "br": 1.14,
      "avgWr": 50.0
    },
    "Rumble": {
      "wr": 48.42,
      "pr": 0.14,
      "br": 0.88,
      "avgWr": 50.0
    },
    "Sejuani": {
      "wr": 50.5,
      "pr": 2.03,
      "br": 0.23,
      "avgWr": 50.0
    },
    "Shaco": {
      "wr": 48.84,
      "pr": 5.6,
      "br": 26.81,
      "avgWr": 50.0
    },
    "Shen": {
      "wr": 51.19,
      "pr": 1.48,
      "br": 1.82,
      "avgWr": 50.0
    },
    "Shyvana": {
      "wr": 52.75,
      "pr": 6.53,
      "br": 9.55,
      "avgWr": 50.0
    },
    "Sett": {
      "wr": 48.8,
      "pr": 0.13,
      "br": 4.49,
      "avgWr": 50.0
    },
    "Singed": {
      "wr": 47.65,
      "pr": 0.1,
      "br": 0.91,
      "avgWr": 50.0
    },
    "Sion": {
      "wr": 51.3,
      "pr": 0.23,
      "br": 1.33,
      "avgWr": 50.0
    },
    "Skarner": {
      "wr": 48.46,
      "pr": 0.69,
      "br": 0.17,
      "avgWr": 50.0
    },
    "Sylas": {
      "wr": 48.63,
      "pr": 4.31,
      "br": 11.12,
      "avgWr": 50.0
    },
    "Tahm Kench": {
      "wr": 44.63,
      "pr": 0.04,
      "br": 4.4,
      "avgWr": 50.0
    },
    "Taliyah": {
      "wr": 49.49,
      "pr": 0.4,
      "br": 0.19,
      "avgWr": 50.0
    },
    "Taric": {
      "wr": 47.2,
      "pr": 0.03,
      "br": 0.3,
      "avgWr": 50.0
    },
    "Talon": {
      "wr": 48.4,
      "pr": 2.91,
      "br": 2.58,
      "avgWr": 50.0
    },
    "Teemo": {
      "wr": 51.0,
      "pr": 1.22,
      "br": 13.01,
      "avgWr": 50.0
    },
    "Trundle": {
      "wr": 50.19,
      "pr": 1.0,
      "br": 0.7,
      "avgWr": 50.0
    },
    "Tryndamere": {
      "wr": 51.36,
      "pr": 0.66,
      "br": 2.78,
      "avgWr": 50.0
    },
    "Twisted Fate": {
      "wr": 40.12,
      "pr": 0.03,
      "br": 0.53,
      "avgWr": 50.0
    },
    "Udyr": {
      "wr": 49.63,
      "pr": 1.63,
      "br": 0.65,
      "avgWr": 50.0
    },
    "Twitch": {
      "wr": 42.07,
      "pr": 0.36,
      "br": 7.76,
      "avgWr": 50.0
    },
    "Urgot": {
      "wr": 47.09,
      "pr": 0.05,
      "br": 1.46,
      "avgWr": 50.0
    },
    "Vayne": {
      "wr": 46.37,
      "pr": 0.2,
      "br": 11.96,
      "avgWr": 50.0
    },
    "Viego": {
      "wr": 49.74,
      "pr": 10.27,
      "br": 10.7,
      "avgWr": 50.0
    },
    "Vi": {
      "wr": 49.82,
      "pr": 4.9,
      "br": 1.17,
      "avgWr": 50.0
    },
    "Warwick": {
      "wr": 50.69,
      "pr": 5.37,
      "br": 4.94,
      "avgWr": 50.0
    },
    "Volibear": {
      "wr": 50.49,
      "pr": 3.25,
      "br": 3.88,
      "avgWr": 50.0
    },
    "Xin Zhao": {
      "wr": 50.81,
      "pr": 5.78,
      "br": 2.65,
      "avgWr": 50.0
    },
    "Yorick": {
      "wr": 49.66,
      "pr": 0.18,
      "br": 12.52,
      "avgWr": 50.0
    },
    "Yone": {
      "wr": 44.75,
      "pr": 0.08,
      "br": 7.01,
      "avgWr": 50.0
    },
    "Zaahen": {
      "wr": 49.77,
      "pr": 1.26,
      "br": 4.15,
      "avgWr": 50.0
    },
    "Zed": {
      "wr": 47.8,
      "pr": 2.12,
      "br": 22.89,
      "avgWr": 50.0
    },
    "Zeri": {
      "wr": 43.8,
      "pr": 0.02,
      "br": 0.21,
      "avgWr": 50.0
    },
    "Zac": {
      "wr": 49.74,
      "pr": 2.03,
      "br": 0.77,
      "avgWr": 50.0
    },
    "Zyra": {
      "wr": 51.37,
      "pr": 0.83,
      "br": 4.19,
      "avgWr": 50.0
    }
  },
  "middle": {
    "Ahri": {
      "wr": 50.35,
      "pr": 10.49,
      "br": 5.28,
      "avgWr": 50.0
    },
    "Akshan": {
      "wr": 49.72,
      "pr": 2.14,
      "br": 1.83,
      "avgWr": 50.0
    },
    "Akali": {
      "wr": 48.97,
      "pr": 7.62,
      "br": 17.85,
      "avgWr": 50.0
    },
    "Aatrox": {
      "wr": 49.29,
      "pr": 0.13,
      "br": 7.75,
      "avgWr": 50.0
    },
    "Ambessa": {
      "wr": 49.86,
      "pr": 0.19,
      "br": 7.17,
      "avgWr": 50.0
    },
    "Alistar": {
      "wr": 42.0,
      "pr": 0.03,
      "br": 1.21,
      "avgWr": 50.0
    },
    "Anivia": {
      "wr": 51.05,
      "pr": 2.7,
      "br": 2.55,
      "avgWr": 50.0
    },
    "Annie": {
      "wr": 50.89,
      "pr": 2.65,
      "br": 0.89,
      "avgWr": 50.0
    },
    "Aphelios": {
      "wr": 44.58,
      "pr": 0.04,
      "br": 2.23,
      "avgWr": 50.0
    },
    "Ashe": {
      "wr": 44.83,
      "pr": 0.19,
      "br": 7.56,
      "avgWr": 50.0
    },
    "Aurelion Sol": {
      "wr": 51.55,
      "pr": 2.88,
      "br": 1.31,
      "avgWr": 50.0
    },
    "Aurora": {
      "wr": 48.85,
      "pr": 3.05,
      "br": 2.16,
      "avgWr": 50.0
    },
    "Azir": {
      "wr": 45.7,
      "pr": 1.95,
      "br": 0.41,
      "avgWr": 50.0
    },
    "Bel'Veth": {
      "wr": 43.12,
      "pr": 0.03,
      "br": 1.49,
      "avgWr": 50.0
    },
    "Brand": {
      "wr": 51.95,
      "pr": 1.89,
      "br": 7.14,
      "avgWr": 50.0
    },
    "Briar": {
      "wr": 53.59,
      "pr": 0.27,
      "br": 14.78,
      "avgWr": 50.0
    },
    "Caitlyn": {
      "wr": 45.15,
      "pr": 0.26,
      "br": 30.31,
      "avgWr": 50.0
    },
    "Camille": {
      "wr": 49.89,
      "pr": 0.05,
      "br": 0.64,
      "avgWr": 50.0
    },
    "Cassiopeia": {
      "wr": 48.61,
      "pr": 1.09,
      "br": 0.94,
      "avgWr": 50.0
    },
    "Cho'Gath": {
      "wr": 50.84,
      "pr": 0.58,
      "br": 1.07,
      "avgWr": 50.0
    },
    "Corki": {
      "wr": 43.53,
      "pr": 0.21,
      "br": 0.43,
      "avgWr": 50.0
    },
    "Diana": {
      "wr": 51.12,
      "pr": 4.3,
      "br": 5.86,
      "avgWr": 50.0
    },
    "Darius": {
      "wr": 47.9,
      "pr": 0.12,
      "br": 16.97,
      "avgWr": 50.0
    },
    "Dr. Mundo": {
      "wr": 49.21,
      "pr": 0.1,
      "br": 8.64,
      "avgWr": 50.0
    },
    "Draven": {
      "wr": 46.57,
      "pr": 0.07,
      "br": 9.68,
      "avgWr": 50.0
    },
    "Ekko": {
      "wr": 50.34,
      "pr": 3.18,
      "br": 2.14,
      "avgWr": 50.0
    },
    "Elise": {
      "wr": 50.89,
      "pr": 0.03,
      "br": 0.86,
      "avgWr": 50.0
    },
    "Evelynn": {
      "wr": 49.54,
      "pr": 0.02,
      "br": 1.83,
      "avgWr": 50.0
    },
    "Ezreal": {
      "wr": 41.98,
      "pr": 0.83,
      "br": 7.18,
      "avgWr": 50.0
    },
    "Fiddlesticks": {
      "wr": 53.2,
      "pr": 0.1,
      "br": 1.16,
      "avgWr": 50.0
    },
    "Fizz": {
      "wr": 51.37,
      "pr": 5.83,
      "br": 9.87,
      "avgWr": 50.0
    },
    "Fiora": {
      "wr": 49.57,
      "pr": 0.04,
      "br": 3.14,
      "avgWr": 50.0
    },
    "Galio": {
      "wr": 49.37,
      "pr": 3.23,
      "br": 1.6,
      "avgWr": 50.0
    },
    "Gangplank": {
      "wr": 50.19,
      "pr": 0.36,
      "br": 2.72,
      "avgWr": 50.0
    },
    "Gnar": {
      "wr": 46.92,
      "pr": 0.04,
      "br": 1.04,
      "avgWr": 50.0
    },
    "Gragas": {
      "wr": 50.31,
      "pr": 0.28,
      "br": 0.42,
      "avgWr": 50.0
    },
    "Garen": {
      "wr": 52.96,
      "pr": 0.55,
      "br": 11.52,
      "avgWr": 50.0
    },
    "Graves": {
      "wr": 47.51,
      "pr": 0.1,
      "br": 10.4,
      "avgWr": 50.0
    },
    "Gwen": {
      "wr": 51.58,
      "pr": 0.33,
      "br": 2.69,
      "avgWr": 50.0
    },
    "Heimerdinger": {
      "wr": 51.3,
      "pr": 0.55,
      "br": 4.49,
      "avgWr": 50.0
    },
    "Hwei": {
      "wr": 50.76,
      "pr": 3.29,
      "br": 1.51,
      "avgWr": 50.0
    },
    "Illaoi": {
      "wr": 51.08,
      "pr": 0.09,
      "br": 8.79,
      "avgWr": 50.0
    },
    "Irelia": {
      "wr": 50.24,
      "pr": 3.02,
      "br": 11.81,
      "avgWr": 50.0
    },
    "Ivern": {
      "wr": 47.92,
      "pr": 0.02,
      "br": 0.29,
      "avgWr": 50.0
    },
    "Jarvan IV": {
      "wr": 49.0,
      "pr": 0.07,
      "br": 1.05,
      "avgWr": 50.0
    },
    "Jax": {
      "wr": 49.31,
      "pr": 0.1,
      "br": 10.21,
      "avgWr": 50.0
    },
    "Jayce": {
      "wr": 49.5,
      "pr": 0.53,
      "br": 2.4,
      "avgWr": 50.0
    },
    "Jhin": {
      "wr": 47.38,
      "pr": 0.23,
      "br": 3.63,
      "avgWr": 50.0
    },
    "K'Sante": {
      "wr": 48.13,
      "pr": 0.07,
      "br": 1.51,
      "avgWr": 50.0
    },
    "Kai'Sa": {
      "wr": 44.15,
      "pr": 0.23,
      "br": 2.2,
      "avgWr": 50.0
    },
    "Kalista": {
      "wr": 50.98,
      "pr": 0.04,
      "br": 0.33,
      "avgWr": 50.0
    },
    "Karma": {
      "wr": 47.97,
      "pr": 0.18,
      "br": 5.26,
      "avgWr": 50.0
    },
    "Karthus": {
      "wr": 48.89,
      "pr": 0.16,
      "br": 0.58,
      "avgWr": 50.0
    },
    "Kassadin": {
      "wr": 49.61,
      "pr": 1.78,
      "br": 1.47,
      "avgWr": 50.0
    },
    "Katarina": {
      "wr": 49.4,
      "pr": 5.95,
      "br": 7.83,
      "avgWr": 50.0
    },
    "Kayle": {
      "wr": 52.13,
      "pr": 0.43,
      "br": 3.54,
      "avgWr": 50.0
    },
    "Kennen": {
      "wr": 51.09,
      "pr": 0.37,
      "br": 1.39,
      "avgWr": 50.0
    },
    "Kindred": {
      "wr": 45.4,
      "pr": 0.02,
      "br": 0.95,
      "avgWr": 50.0
    },
    "Kled": {
      "wr": 53.56,
      "pr": 0.09,
      "br": 0.76,
      "avgWr": 50.0
    },
    "Kog'Maw": {
      "wr": 51.09,
      "pr": 0.25,
      "br": 0.45,
      "avgWr": 50.0
    },
    "LeBlanc": {
      "wr": 49.09,
      "pr": 4.05,
      "br": 12.67,
      "avgWr": 50.0
    },
    "Lee Sin": {
      "wr": 44.55,
      "pr": 0.11,
      "br": 11.06,
      "avgWr": 50.0
    },
    "Lillia": {
      "wr": 47.99,
      "pr": 0.02,
      "br": 2.14,
      "avgWr": 50.0
    },
    "Lissandra": {
      "wr": 50.93,
      "pr": 4.12,
      "br": 2.18,
      "avgWr": 50.0
    },
    "Lucian": {
      "wr": 42.23,
      "pr": 0.2,
      "br": 2.14,
      "avgWr": 50.0
    },
    "Lux": {
      "wr": 51.34,
      "pr": 4.94,
      "br": 13.06,
      "avgWr": 50.0
    },
    "Malphite": {
      "wr": 51.56,
      "pr": 1.13,
      "br": 17.28,
      "avgWr": 50.0
    },
    "Maokai": {
      "wr": 49.62,
      "pr": 0.02,
      "br": 0.31,
      "avgWr": 50.0
    },
    "Malzahar": {
      "wr": 52.02,
      "pr": 8.92,
      "br": 16.67,
      "avgWr": 50.0
    },
    "Master Yi": {
      "wr": 49.8,
      "pr": 0.15,
      "br": 19.04,
      "avgWr": 50.0
    },
    "Mel": {
      "wr": 47.16,
      "pr": 6.0,
      "br": 39.41,
      "avgWr": 50.0
    },
    "Miss Fortune": {
      "wr": 44.59,
      "pr": 0.19,
      "br": 6.26,
      "avgWr": 50.0
    },
    "Mordekaiser": {
      "wr": 52.86,
      "pr": 0.25,
      "br": 14.37,
      "avgWr": 50.0
    },
    "Morgana": {
      "wr": 51.29,
      "pr": 0.88,
      "br": 24.06,
      "avgWr": 50.0
    },
    "Naafiri": {
      "wr": 51.94,
      "pr": 3.41,
      "br": 19.43,
      "avgWr": 50.0
    },
    "Nasus": {
      "wr": 52.45,
      "pr": 0.53,
      "br": 5.23,
      "avgWr": 50.0
    },
    "Neeko": {
      "wr": 49.94,
      "pr": 0.48,
      "br": 1.42,
      "avgWr": 50.0
    },
    "Nidalee": {
      "wr": 45.6,
      "pr": 0.05,
      "br": 0.51,
      "avgWr": 50.0
    },
    "Nilah": {
      "wr": 41.58,
      "pr": 0.01,
      "br": 2.47,
      "avgWr": 50.0
    },
    "Nocturne": {
      "wr": 50.79,
      "pr": 0.08,
      "br": 15.13,
      "avgWr": 50.0
    },
    "Nunu & Willump": {
      "wr": 49.02,
      "pr": 0.13,
      "br": 0.55,
      "avgWr": 50.0
    },
    "Olaf": {
      "wr": 50.59,
      "pr": 0.04,
      "br": 1.8,
      "avgWr": 50.0
    },
    "Orianna": {
      "wr": 47.53,
      "pr": 3.32,
      "br": 0.7,
      "avgWr": 50.0
    },
    "Ornn": {
      "wr": 50.41,
      "pr": 0.06,
      "br": 0.81,
      "avgWr": 50.0
    },
    "Pantheon": {
      "wr": 51.43,
      "pr": 1.03,
      "br": 2.24,
      "avgWr": 50.0
    },
    "Poppy": {
      "wr": 51.46,
      "pr": 0.03,
      "br": 1.5,
      "avgWr": 50.0
    },
    "Pyke": {
      "wr": 45.99,
      "pr": 0.07,
      "br": 16.71,
      "avgWr": 50.0
    },
    "Qiyana": {
      "wr": 48.02,
      "pr": 1.61,
      "br": 0.82,
      "avgWr": 50.0
    },
    "Rakan": {
      "wr": 49.25,
      "pr": 0.03,
      "br": 0.29,
      "avgWr": 50.0
    },
    "Quinn": {
      "wr": 50.73,
      "pr": 0.33,
      "br": 1.15,
      "avgWr": 50.0
    },
    "Rek'Sai": {
      "wr": 50.13,
      "pr": 0.02,
      "br": 0.79,
      "avgWr": 50.0
    },
    "Renekton": {
      "wr": 51.43,
      "pr": 0.26,
      "br": 3.2,
      "avgWr": 50.0
    },
    "Riven": {
      "wr": 50.9,
      "pr": 0.2,
      "br": 1.14,
      "avgWr": 50.0
    },
    "Rumble": {
      "wr": 50.28,
      "pr": 0.14,
      "br": 0.88,
      "avgWr": 50.0
    },
    "Ryze": {
      "wr": 47.24,
      "pr": 2.6,
      "br": 0.63,
      "avgWr": 50.0
    },
    "Samira": {
      "wr": 45.01,
      "pr": 0.05,
      "br": 11.44,
      "avgWr": 50.0
    },
    "Sejuani": {
      "wr": 51.65,
      "pr": 0.05,
      "br": 0.23,
      "avgWr": 50.0
    },
    "Seraphine": {
      "wr": 49.57,
      "pr": 0.24,
      "br": 3.64,
      "avgWr": 50.0
    },
    "Senna": {
      "wr": 45.61,
      "pr": 0.06,
      "br": 1.2,
      "avgWr": 50.0
    },
    "Shaco": {
      "wr": 45.14,
      "pr": 0.05,
      "br": 26.81,
      "avgWr": 50.0
    },
    "Shen": {
      "wr": 52.08,
      "pr": 0.1,
      "br": 1.82,
      "avgWr": 50.0
    },
    "Shyvana": {
      "wr": 45.9,
      "pr": 0.04,
      "br": 9.55,
      "avgWr": 50.0
    },
    "Sett": {
      "wr": 52.91,
      "pr": 0.22,
      "br": 4.49,
      "avgWr": 50.0
    },
    "Singed": {
      "wr": 55.58,
      "pr": 0.16,
      "br": 0.91,
      "avgWr": 50.0
    },
    "Sion": {
      "wr": 53.54,
      "pr": 0.93,
      "br": 1.33,
      "avgWr": 50.0
    },
    "Sivir": {
      "wr": 41.9,
      "pr": 0.04,
      "br": 2.32,
      "avgWr": 50.0
    },
    "Skarner": {
      "wr": 45.3,
      "pr": 0.01,
      "br": 0.17,
      "avgWr": 50.0
    },
    "Smolder": {
      "wr": 47.55,
      "pr": 1.07,
      "br": 6.02,
      "avgWr": 50.0
    },
    "Soraka": {
      "wr": 45.74,
      "pr": 0.03,
      "br": 2.48,
      "avgWr": 50.0
    },
    "Swain": {
      "wr": 51.5,
      "pr": 0.95,
      "br": 5.83,
      "avgWr": 50.0
    },
    "Syndra": {
      "wr": 49.94,
      "pr": 3.6,
      "br": 2.27,
      "avgWr": 50.0
    },
    "Sylas": {
      "wr": 48.77,
      "pr": 6.41,
      "br": 11.12,
      "avgWr": 50.0
    },
    "Tahm Kench": {
      "wr": 51.3,
      "pr": 0.11,
      "br": 4.4,
      "avgWr": 50.0
    },
    "Taliyah": {
      "wr": 47.06,
      "pr": 0.94,
      "br": 0.19,
      "avgWr": 50.0
    },
    "Talon": {
      "wr": 48.18,
      "pr": 2.4,
      "br": 2.58,
      "avgWr": 50.0
    },
    "Teemo": {
      "wr": 50.07,
      "pr": 0.34,
      "br": 13.01,
      "avgWr": 50.0
    },
    "Trundle": {
      "wr": 48.7,
      "pr": 0.04,
      "br": 0.7,
      "avgWr": 50.0
    },
    "Tristana": {
      "wr": 46.31,
      "pr": 0.46,
      "br": 2.38,
      "avgWr": 50.0
    },
    "Tryndamere": {
      "wr": 52.46,
      "pr": 0.31,
      "br": 2.78,
      "avgWr": 50.0
    },
    "Twisted Fate": {
      "wr": 50.12,
      "pr": 3.34,
      "br": 0.53,
      "avgWr": 50.0
    },
    "Udyr": {
      "wr": 47.5,
      "pr": 0.04,
      "br": 0.65,
      "avgWr": 50.0
    },
    "Twitch": {
      "wr": 47.26,
      "pr": 0.15,
      "br": 7.76,
      "avgWr": 50.0
    },
    "Urgot": {
      "wr": 50.83,
      "pr": 0.06,
      "br": 1.46,
      "avgWr": 50.0
    },
    "Varus": {
      "wr": 46.32,
      "pr": 0.36,
      "br": 2.51,
      "avgWr": 50.0
    },
    "Veigar": {
      "wr": 52.21,
      "pr": 6.73,
      "br": 4.05,
      "avgWr": 50.0
    },
    "Vayne": {
      "wr": 48.56,
      "pr": 0.19,
      "br": 11.96,
      "avgWr": 50.0
    },
    "Vel'Koz": {
      "wr": 50.93,
      "pr": 1.07,
      "br": 1.61,
      "avgWr": 50.0
    },
    "Vex": {
      "wr": 50.79,
      "pr": 3.76,
      "br": 4.19,
      "avgWr": 50.0
    },
    "Viego": {
      "wr": 49.58,
      "pr": 0.23,
      "br": 10.7,
      "avgWr": 50.0
    },
    "Vi": {
      "wr": 48.08,
      "pr": 0.07,
      "br": 1.17,
      "avgWr": 50.0
    },
    "Viktor": {
      "wr": 51.22,
      "pr": 5.47,
      "br": 2.98,
      "avgWr": 50.0
    },
    "Vladimir": {
      "wr": 50.47,
      "pr": 2.94,
      "br": 3.38,
      "avgWr": 50.0
    },
    "Warwick": {
      "wr": 50.59,
      "pr": 0.04,
      "br": 4.94,
      "avgWr": 50.0
    },
    "Volibear": {
      "wr": 49.59,
      "pr": 0.07,
      "br": 3.88,
      "avgWr": 50.0
    },
    "Xayah": {
      "wr": 45.6,
      "pr": 0.02,
      "br": 0.64,
      "avgWr": 50.0
    },
    "Xerath": {
      "wr": 52.08,
      "pr": 5.25,
      "br": 10.64,
      "avgWr": 50.0
    },
    "Xin Zhao": {
      "wr": 51.6,
      "pr": 0.36,
      "br": 2.65,
      "avgWr": 50.0
    },
    "Yasuo": {
      "wr": 49.53,
      "pr": 10.17,
      "br": 20.71,
      "avgWr": 50.0
    },
    "Yorick": {
      "wr": 50.6,
      "pr": 0.26,
      "br": 12.52,
      "avgWr": 50.0
    },
    "Yunara": {
      "wr": 40.49,
      "pr": 0.03,
      "br": 2.48,
      "avgWr": 50.0
    },
    "Yone": {
      "wr": 49.4,
      "pr": 7.23,
      "br": 7.01,
      "avgWr": 50.0
    },
    "Zaahen": {
      "wr": 48.12,
      "pr": 0.06,
      "br": 4.15,
      "avgWr": 50.0
    },
    "Zed": {
      "wr": 49.23,
      "pr": 7.49,
      "br": 22.89,
      "avgWr": 50.0
    },
    "Zeri": {
      "wr": 44.48,
      "pr": 0.04,
      "br": 0.21,
      "avgWr": 50.0
    },
    "Zac": {
      "wr": 52.99,
      "pr": 0.1,
      "br": 0.77,
      "avgWr": 50.0
    },
    "Ziggs": {
      "wr": 50.38,
      "pr": 1.13,
      "br": 0.76,
      "avgWr": 50.0
    },
    "Zilean": {
      "wr": 53.43,
      "pr": 0.19,
      "br": 0.8,
      "avgWr": 50.0
    },
    "Zoe": {
      "wr": 48.65,
      "pr": 3.03,
      "br": 3.48,
      "avgWr": 50.0
    },
    "Zyra": {
      "wr": 50.01,
      "pr": 0.26,
      "br": 4.19,
      "avgWr": 50.0
    }
  },
  "bottom": {
    "Ahri": {
      "wr": 47.98,
      "pr": 0.05,
      "br": 5.28,
      "avgWr": 50.0
    },
    "Akshan": {
      "wr": 48.05,
      "pr": 0.1,
      "br": 1.83,
      "avgWr": 50.0
    },
    "Anivia": {
      "wr": 47.32,
      "pr": 0.07,
      "br": 2.55,
      "avgWr": 50.0
    },
    "Annie": {
      "wr": 49.15,
      "pr": 0.04,
      "br": 0.89,
      "avgWr": 50.0
    },
    "Aphelios": {
      "wr": 49.25,
      "pr": 3.75,
      "br": 2.23,
      "avgWr": 50.0
    },
    "Ashe": {
      "wr": 51.17,
      "pr": 15.16,
      "br": 7.56,
      "avgWr": 50.0
    },
    "Aurelion Sol": {
      "wr": 53.48,
      "pr": 0.47,
      "br": 1.31,
      "avgWr": 50.0
    },
    "Aurora": {
      "wr": 48.26,
      "pr": 0.04,
      "br": 2.16,
      "avgWr": 50.0
    },
    "Azir": {
      "wr": 41.72,
      "pr": 0.02,
      "br": 0.41,
      "avgWr": 50.0
    },
    "Brand": {
      "wr": 54.09,
      "pr": 0.98,
      "br": 7.14,
      "avgWr": 50.0
    },
    "Caitlyn": {
      "wr": 49.95,
      "pr": 20.34,
      "br": 30.31,
      "avgWr": 50.0
    },
    "Cassiopeia": {
      "wr": 51.18,
      "pr": 0.16,
      "br": 0.94,
      "avgWr": 50.0
    },
    "Cho'Gath": {
      "wr": 46.71,
      "pr": 0.05,
      "br": 1.07,
      "avgWr": 50.0
    },
    "Corki": {
      "wr": 47.94,
      "pr": 1.94,
      "br": 0.43,
      "avgWr": 50.0
    },
    "Draven": {
      "wr": 48.76,
      "pr": 3.7,
      "br": 9.68,
      "avgWr": 50.0
    },
    "Ezreal": {
      "wr": 47.62,
      "pr": 16.05,
      "br": 7.18,
      "avgWr": 50.0
    },
    "Fiora": {
      "wr": 51.35,
      "pr": 0.02,
      "br": 3.14,
      "avgWr": 50.0
    },
    "Heimerdinger": {
      "wr": 51.78,
      "pr": 0.12,
      "br": 4.49,
      "avgWr": 50.0
    },
    "Hwei": {
      "wr": 52.99,
      "pr": 0.33,
      "br": 1.51,
      "avgWr": 50.0
    },
    "Irelia": {
      "wr": 48.31,
      "pr": 0.07,
      "br": 11.81,
      "avgWr": 50.0
    },
    "Jayce": {
      "wr": 43.93,
      "pr": 0.02,
      "br": 2.4,
      "avgWr": 50.0
    },
    "Jinx": {
      "wr": 51.32,
      "pr": 14.27,
      "br": 5.55,
      "avgWr": 50.0
    },
    "Jhin": {
      "wr": 49.75,
      "pr": 16.68,
      "br": 3.63,
      "avgWr": 50.0
    },
    "Kai'Sa": {
      "wr": 48.49,
      "pr": 12.95,
      "br": 2.2,
      "avgWr": 50.0
    },
    "Kalista": {
      "wr": 47.07,
      "pr": 1.26,
      "br": 0.33,
      "avgWr": 50.0
    },
    "Karthus": {
      "wr": 53.8,
      "pr": 0.29,
      "br": 0.58,
      "avgWr": 50.0
    },
    "Katarina": {
      "wr": 53.07,
      "pr": 0.35,
      "br": 7.83,
      "avgWr": 50.0
    },
    "Kayle": {
      "wr": 49.67,
      "pr": 0.03,
      "br": 3.54,
      "avgWr": 50.0
    },
    "Kennen": {
      "wr": 41.46,
      "pr": 0.08,
      "br": 1.39,
      "avgWr": 50.0
    },
    "Kindred": {
      "wr": 46.89,
      "pr": 0.05,
      "br": 0.95,
      "avgWr": 50.0
    },
    "Kled": {
      "wr": 48.78,
      "pr": 0.01,
      "br": 0.76,
      "avgWr": 50.0
    },
    "Kog'Maw": {
      "wr": 52.39,
      "pr": 1.53,
      "br": 0.45,
      "avgWr": 50.0
    },
    "Lucian": {
      "wr": 48.63,
      "pr": 6.95,
      "br": 2.14,
      "avgWr": 50.0
    },
    "Lux": {
      "wr": 51.78,
      "pr": 0.53,
      "br": 13.06,
      "avgWr": 50.0
    },
    "Malzahar": {
      "wr": 50.55,
      "pr": 0.19,
      "br": 16.67,
      "avgWr": 50.0
    },
    "Master Yi": {
      "wr": 53.83,
      "pr": 0.06,
      "br": 19.04,
      "avgWr": 50.0
    },
    "Mel": {
      "wr": 48.13,
      "pr": 1.06,
      "br": 39.41,
      "avgWr": 50.0
    },
    "Miss Fortune": {
      "wr": 51.31,
      "pr": 14.75,
      "br": 6.26,
      "avgWr": 50.0
    },
    "Morgana": {
      "wr": 45.12,
      "pr": 0.07,
      "br": 24.06,
      "avgWr": 50.0
    },
    "Naafiri": {
      "wr": 51.04,
      "pr": 0.06,
      "br": 19.43,
      "avgWr": 50.0
    },
    "Neeko": {
      "wr": 42.96,
      "pr": 0.03,
      "br": 1.42,
      "avgWr": 50.0
    },
    "Nidalee": {
      "wr": 44.3,
      "pr": 0.01,
      "br": 0.51,
      "avgWr": 50.0
    },
    "Nilah": {
      "wr": 52.85,
      "pr": 1.44,
      "br": 2.47,
      "avgWr": 50.0
    },
    "Olaf": {
      "wr": 53.99,
      "pr": 0.02,
      "br": 1.8,
      "avgWr": 50.0
    },
    "Orianna": {
      "wr": 43.86,
      "pr": 0.02,
      "br": 0.7,
      "avgWr": 50.0
    },
    "Pantheon": {
      "wr": 45.35,
      "pr": 0.04,
      "br": 2.24,
      "avgWr": 50.0
    },
    "Qiyana": {
      "wr": 47.01,
      "pr": 0.01,
      "br": 0.82,
      "avgWr": 50.0
    },
    "Quinn": {
      "wr": 47.93,
      "pr": 0.07,
      "br": 1.15,
      "avgWr": 50.0
    },
    "Rengar": {
      "wr": 45.69,
      "pr": 0.03,
      "br": 3.45,
      "avgWr": 50.0
    },
    "Ryze": {
      "wr": 47.0,
      "pr": 0.03,
      "br": 0.63,
      "avgWr": 50.0
    },
    "Samira": {
      "wr": 50.89,
      "pr": 6.01,
      "br": 11.44,
      "avgWr": 50.0
    },
    "Senna": {
      "wr": 50.99,
      "pr": 2.51,
      "br": 1.2,
      "avgWr": 50.0
    },
    "Seraphine": {
      "wr": 52.39,
      "pr": 0.38,
      "br": 3.64,
      "avgWr": 50.0
    },
    "Singed": {
      "wr": 50.95,
      "pr": 0.04,
      "br": 0.91,
      "avgWr": 50.0
    },
    "Sion": {
      "wr": 47.31,
      "pr": 0.07,
      "br": 1.33,
      "avgWr": 50.0
    },
    "Sivir": {
      "wr": 49.93,
      "pr": 3.82,
      "br": 2.32,
      "avgWr": 50.0
    },
    "Smolder": {
      "wr": 52.41,
      "pr": 10.41,
      "br": 6.02,
      "avgWr": 50.0
    },
    "Swain": {
      "wr": 53.8,
      "pr": 1.18,
      "br": 5.83,
      "avgWr": 50.0
    },
    "Syndra": {
      "wr": 51.43,
      "pr": 0.11,
      "br": 2.27,
      "avgWr": 50.0
    },
    "Tahm Kench": {
      "wr": 52.03,
      "pr": 0.09,
      "br": 4.4,
      "avgWr": 50.0
    },
    "Taliyah": {
      "wr": 47.05,
      "pr": 0.03,
      "br": 0.19,
      "avgWr": 50.0
    },
    "Teemo": {
      "wr": 48.32,
      "pr": 0.16,
      "br": 13.01,
      "avgWr": 50.0
    },
    "Tristana": {
      "wr": 48.81,
      "pr": 5.37,
      "br": 2.38,
      "avgWr": 50.0
    },
    "Twisted Fate": {
      "wr": 46.33,
      "pr": 0.11,
      "br": 0.53,
      "avgWr": 50.0
    },
    "Twitch": {
      "wr": 50.8,
      "pr": 5.03,
      "br": 7.76,
      "avgWr": 50.0
    },
    "Urgot": {
      "wr": 46.79,
      "pr": 0.02,
      "br": 1.46,
      "avgWr": 50.0
    },
    "Varus": {
      "wr": 46.95,
      "pr": 3.85,
      "br": 2.51,
      "avgWr": 50.0
    },
    "Veigar": {
      "wr": 53.56,
      "pr": 1.12,
      "br": 4.05,
      "avgWr": 50.0
    },
    "Vayne": {
      "wr": 50.39,
      "pr": 7.35,
      "br": 11.96,
      "avgWr": 50.0
    },
    "Vel'Koz": {
      "wr": 53.19,
      "pr": 0.33,
      "br": 1.61,
      "avgWr": 50.0
    },
    "Vex": {
      "wr": 47.71,
      "pr": 0.03,
      "br": 4.19,
      "avgWr": 50.0
    },
    "Viktor": {
      "wr": 52.65,
      "pr": 0.11,
      "br": 2.98,
      "avgWr": 50.0
    },
    "Vladimir": {
      "wr": 51.84,
      "pr": 0.27,
      "br": 3.38,
      "avgWr": 50.0
    },
    "Xayah": {
      "wr": 50.48,
      "pr": 3.42,
      "br": 0.64,
      "avgWr": 50.0
    },
    "Xerath": {
      "wr": 53.22,
      "pr": 0.3,
      "br": 10.64,
      "avgWr": 50.0
    },
    "Yasuo": {
      "wr": 51.38,
      "pr": 1.09,
      "br": 20.71,
      "avgWr": 50.0
    },
    "Yunara": {
      "wr": 47.85,
      "pr": 5.87,
      "br": 2.48,
      "avgWr": 50.0
    },
    "Yone": {
      "wr": 49.2,
      "pr": 0.12,
      "br": 7.01,
      "avgWr": 50.0
    },
    "Zeri": {
      "wr": 48.94,
      "pr": 1.65,
      "br": 0.21,
      "avgWr": 50.0
    },
    "Ziggs": {
      "wr": 51.74,
      "pr": 1.67,
      "br": 0.76,
      "avgWr": 50.0
    },
    "Zilean": {
      "wr": 52.11,
      "pr": 0.02,
      "br": 0.8,
      "avgWr": 50.0
    },
    "Zoe": {
      "wr": 44.91,
      "pr": 0.03,
      "br": 3.48,
      "avgWr": 50.0
    },
    "Zyra": {
      "wr": 51.16,
      "pr": 0.08,
      "br": 4.19,
      "avgWr": 50.0
    }
  },
  "support": {
    "Ahri": {
      "wr": 47.28,
      "pr": 0.16,
      "br": 5.28,
      "avgWr": 50.0
    },
    "Akshan": {
      "wr": 42.4,
      "pr": 0.03,
      "br": 1.83,
      "avgWr": 50.0
    },
    "Aatrox": {
      "wr": 41.97,
      "pr": 0.05,
      "br": 7.75,
      "avgWr": 50.0
    },
    "Amumu": {
      "wr": 51.22,
      "pr": 0.49,
      "br": 2.65,
      "avgWr": 50.0
    },
    "Alistar": {
      "wr": 49.29,
      "pr": 3.0,
      "br": 1.21,
      "avgWr": 50.0
    },
    "Anivia": {
      "wr": 48.14,
      "pr": 1.02,
      "br": 2.55,
      "avgWr": 50.0
    },
    "Annie": {
      "wr": 50.25,
      "pr": 0.36,
      "br": 0.89,
      "avgWr": 50.0
    },
    "Ashe": {
      "wr": 45.54,
      "pr": 1.23,
      "br": 7.56,
      "avgWr": 50.0
    },
    "Aurelion Sol": {
      "wr": 48.35,
      "pr": 0.13,
      "br": 1.31,
      "avgWr": 50.0
    },
    "Aurora": {
      "wr": 44.83,
      "pr": 0.05,
      "br": 2.16,
      "avgWr": 50.0
    },
    "Azir": {
      "wr": 36.86,
      "pr": 0.02,
      "br": 0.41,
      "avgWr": 50.0
    },
    "Bard": {
      "wr": 50.2,
      "pr": 3.73,
      "br": 1.36,
      "avgWr": 50.0
    },
    "Blitzcrank": {
      "wr": 49.86,
      "pr": 5.54,
      "br": 13.99,
      "avgWr": 50.0
    },
    "Bel'Veth": {
      "wr": 43.61,
      "pr": 0.01,
      "br": 1.49,
      "avgWr": 50.0
    },
    "Brand": {
      "wr": 51.96,
      "pr": 5.08,
      "br": 7.14,
      "avgWr": 50.0
    },
    "Braum": {
      "wr": 50.73,
      "pr": 4.85,
      "br": 4.84,
      "avgWr": 50.0
    },
    "Briar": {
      "wr": 45.12,
      "pr": 0.08,
      "br": 14.78,
      "avgWr": 50.0
    },
    "Camille": {
      "wr": 46.84,
      "pr": 0.32,
      "br": 0.64,
      "avgWr": 50.0
    },
    "Cassiopeia": {
      "wr": 46.97,
      "pr": 0.03,
      "br": 0.94,
      "avgWr": 50.0
    },
    "Cho'Gath": {
      "wr": 46.93,
      "pr": 0.26,
      "br": 1.07,
      "avgWr": 50.0
    },
    "Corki": {
      "wr": 37.93,
      "pr": 0.01,
      "br": 0.43,
      "avgWr": 50.0
    },
    "Diana": {
      "wr": 44.59,
      "pr": 0.04,
      "br": 5.86,
      "avgWr": 50.0
    },
    "Darius": {
      "wr": 42.45,
      "pr": 0.07,
      "br": 16.97,
      "avgWr": 50.0
    },
    "Dr. Mundo": {
      "wr": 45.47,
      "pr": 0.09,
      "br": 8.64,
      "avgWr": 50.0
    },
    "Ekko": {
      "wr": 46.73,
      "pr": 0.08,
      "br": 2.14,
      "avgWr": 50.0
    },
    "Elise": {
      "wr": 50.42,
      "pr": 0.54,
      "br": 0.86,
      "avgWr": 50.0
    },
    "Evelynn": {
      "wr": 49.66,
      "pr": 0.04,
      "br": 1.83,
      "avgWr": 50.0
    },
    "Ezreal": {
      "wr": 42.72,
      "pr": 0.52,
      "br": 7.18,
      "avgWr": 50.0
    },
    "Fiddlesticks": {
      "wr": 50.97,
      "pr": 0.52,
      "br": 1.16,
      "avgWr": 50.0
    },
    "Fizz": {
      "wr": 47.73,
      "pr": 0.1,
      "br": 9.87,
      "avgWr": 50.0
    },
    "Fiora": {
      "wr": 43.98,
      "pr": 0.02,
      "br": 3.14,
      "avgWr": 50.0
    },
    "Galio": {
      "wr": 49.34,
      "pr": 0.72,
      "br": 1.6,
      "avgWr": 50.0
    },
    "Gangplank": {
      "wr": 37.58,
      "pr": 0.02,
      "br": 2.72,
      "avgWr": 50.0
    },
    "Gnar": {
      "wr": 40.73,
      "pr": 0.02,
      "br": 1.04,
      "avgWr": 50.0
    },
    "Gragas": {
      "wr": 48.08,
      "pr": 0.19,
      "br": 0.42,
      "avgWr": 50.0
    },
    "Garen": {
      "wr": 39.96,
      "pr": 0.06,
      "br": 11.52,
      "avgWr": 50.0
    },
    "Heimerdinger": {
      "wr": 48.41,
      "pr": 0.27,
      "br": 4.49,
      "avgWr": 50.0
    },
    "Hwei": {
      "wr": 50.17,
      "pr": 0.58,
      "br": 1.51,
      "avgWr": 50.0
    },
    "Illaoi": {
      "wr": 42.27,
      "pr": 0.04,
      "br": 8.79,
      "avgWr": 50.0
    },
    "Ivern": {
      "wr": 48.63,
      "pr": 0.16,
      "br": 0.29,
      "avgWr": 50.0
    },
    "Janna": {
      "wr": 51.72,
      "pr": 2.14,
      "br": 0.38,
      "avgWr": 50.0
    },
    "Jarvan IV": {
      "wr": 49.28,
      "pr": 0.3,
      "br": 1.05,
      "avgWr": 50.0
    },
    "Jax": {
      "wr": 46.19,
      "pr": 0.09,
      "br": 10.21,
      "avgWr": 50.0
    },
    "Jayce": {
      "wr": 43.75,
      "pr": 0.03,
      "br": 2.4,
      "avgWr": 50.0
    },
    "Jhin": {
      "wr": 41.12,
      "pr": 0.13,
      "br": 3.63,
      "avgWr": 50.0
    },
    "K'Sante": {
      "wr": 42.63,
      "pr": 0.07,
      "br": 1.51,
      "avgWr": 50.0
    },
    "Kalista": {
      "wr": 34.02,
      "pr": 0.01,
      "br": 0.33,
      "avgWr": 50.0
    },
    "Karma": {
      "wr": 49.9,
      "pr": 6.63,
      "br": 5.26,
      "avgWr": 50.0
    },
    "Karthus": {
      "wr": 45.64,
      "pr": 0.06,
      "br": 0.58,
      "avgWr": 50.0
    },
    "Katarina": {
      "wr": 42.59,
      "pr": 0.05,
      "br": 7.83,
      "avgWr": 50.0
    },
    "Kayle": {
      "wr": 46.89,
      "pr": 0.05,
      "br": 3.54,
      "avgWr": 50.0
    },
    "Kennen": {
      "wr": 48.69,
      "pr": 0.08,
      "br": 1.39,
      "avgWr": 50.0
    },
    "Kled": {
      "wr": 47.16,
      "pr": 0.03,
      "br": 0.76,
      "avgWr": 50.0
    },
    "Kog'Maw": {
      "wr": 48.67,
      "pr": 0.06,
      "br": 0.45,
      "avgWr": 50.0
    },
    "LeBlanc": {
      "wr": 49.6,
      "pr": 0.54,
      "br": 12.67,
      "avgWr": 50.0
    },
    "Leona": {
      "wr": 51.27,
      "pr": 7.69,
      "br": 9.27,
      "avgWr": 50.0
    },
    "Lee Sin": {
      "wr": 43.98,
      "pr": 0.27,
      "br": 11.06,
      "avgWr": 50.0
    },
    "Lillia": {
      "wr": 43.84,
      "pr": 0.02,
      "br": 2.14,
      "avgWr": 50.0
    },
    "Lissandra": {
      "wr": 48.2,
      "pr": 0.17,
      "br": 2.18,
      "avgWr": 50.0
    },
    "Lulu": {
      "wr": 49.7,
      "pr": 6.98,
      "br": 6.08,
      "avgWr": 50.0
    },
    "Lux": {
      "wr": 50.09,
      "pr": 11.99,
      "br": 13.06,
      "avgWr": 50.0
    },
    "Malphite": {
      "wr": 47.54,
      "pr": 1.27,
      "br": 17.28,
      "avgWr": 50.0
    },
    "Maokai": {
      "wr": 51.12,
      "pr": 2.22,
      "br": 0.31,
      "avgWr": 50.0
    },
    "Malzahar": {
      "wr": 45.75,
      "pr": 0.24,
      "br": 16.67,
      "avgWr": 50.0
    },
    "Master Yi": {
      "wr": 45.94,
      "pr": 0.08,
      "br": 19.04,
      "avgWr": 50.0
    },
    "Milio": {
      "wr": 52.19,
      "pr": 5.26,
      "br": 3.6,
      "avgWr": 50.0
    },
    "Mel": {
      "wr": 45.03,
      "pr": 4.11,
      "br": 39.41,
      "avgWr": 50.0
    },
    "Miss Fortune": {
      "wr": 42.77,
      "pr": 0.55,
      "br": 6.26,
      "avgWr": 50.0
    },
    "Mordekaiser": {
      "wr": 42.41,
      "pr": 0.08,
      "br": 14.37,
      "avgWr": 50.0
    },
    "Nami": {
      "wr": 51.7,
      "pr": 9.62,
      "br": 2.68,
      "avgWr": 50.0
    },
    "Morgana": {
      "wr": 50.8,
      "pr": 8.03,
      "br": 24.06,
      "avgWr": 50.0
    },
    "Naafiri": {
      "wr": 44.83,
      "pr": 0.06,
      "br": 19.43,
      "avgWr": 50.0
    },
    "Nasus": {
      "wr": 42.19,
      "pr": 0.06,
      "br": 5.23,
      "avgWr": 50.0
    },
    "Nautilus": {
      "wr": 49.62,
      "pr": 9.85,
      "br": 13.34,
      "avgWr": 50.0
    },
    "Neeko": {
      "wr": 48.13,
      "pr": 2.52,
      "br": 1.42,
      "avgWr": 50.0
    },
    "Nidalee": {
      "wr": 49.02,
      "pr": 0.27,
      "br": 0.51,
      "avgWr": 50.0
    },
    "Nunu & Willump": {
      "wr": 45.38,
      "pr": 0.1,
      "br": 0.55,
      "avgWr": 50.0
    },
    "Orianna": {
      "wr": 45.73,
      "pr": 0.08,
      "br": 0.7,
      "avgWr": 50.0
    },
    "Ornn": {
      "wr": 45.86,
      "pr": 0.11,
      "br": 0.81,
      "avgWr": 50.0
    },
    "Pantheon": {
      "wr": 48.5,
      "pr": 3.89,
      "br": 2.24,
      "avgWr": 50.0
    },
    "Poppy": {
      "wr": 50.43,
      "pr": 1.49,
      "br": 1.5,
      "avgWr": 50.0
    },
    "Pyke": {
      "wr": 48.35,
      "pr": 5.79,
      "br": 16.71,
      "avgWr": 50.0
    },
    "Qiyana": {
      "wr": 46.69,
      "pr": 0.06,
      "br": 0.82,
      "avgWr": 50.0
    },
    "Rakan": {
      "wr": 49.48,
      "pr": 2.44,
      "br": 0.29,
      "avgWr": 50.0
    },
    "Quinn": {
      "wr": 46.84,
      "pr": 0.06,
      "br": 1.15,
      "avgWr": 50.0
    },
    "Rammus": {
      "wr": 50.34,
      "pr": 0.09,
      "br": 5.73,
      "avgWr": 50.0
    },
    "Rek'Sai": {
      "wr": 46.65,
      "pr": 0.03,
      "br": 0.79,
      "avgWr": 50.0
    },
    "Rell": {
      "wr": 51.23,
      "pr": 2.69,
      "br": 0.87,
      "avgWr": 50.0
    },
    "Renata Glasc": {
      "wr": 50.41,
      "pr": 0.8,
      "br": 0.16,
      "avgWr": 50.0
    },
    "Rengar": {
      "wr": 44.11,
      "pr": 0.07,
      "br": 3.45,
      "avgWr": 50.0
    },
    "Riven": {
      "wr": 41.25,
      "pr": 0.02,
      "br": 1.14,
      "avgWr": 50.0
    },
    "Rumble": {
      "wr": 45.6,
      "pr": 0.06,
      "br": 0.88,
      "avgWr": 50.0
    },
    "Ryze": {
      "wr": 40.58,
      "pr": 0.02,
      "br": 0.63,
      "avgWr": 50.0
    },
    "Senna": {
      "wr": 49.34,
      "pr": 4.69,
      "br": 1.2,
      "avgWr": 50.0
    },
    "Sejuani": {
      "wr": 47.78,
      "pr": 0.09,
      "br": 0.23,
      "avgWr": 50.0
    },
    "Seraphine": {
      "wr": 51.66,
      "pr": 9.75,
      "br": 3.64,
      "avgWr": 50.0
    },
    "Shaco": {
      "wr": 49.88,
      "pr": 1.36,
      "br": 26.81,
      "avgWr": 50.0
    },
    "Shen": {
      "wr": 50.03,
      "pr": 0.88,
      "br": 1.82,
      "avgWr": 50.0
    },
    "Sett": {
      "wr": 47.49,
      "pr": 0.28,
      "br": 4.49,
      "avgWr": 50.0
    },
    "Singed": {
      "wr": 47.16,
      "pr": 0.11,
      "br": 0.91,
      "avgWr": 50.0
    },
    "Sion": {
      "wr": 49.52,
      "pr": 0.32,
      "br": 1.33,
      "avgWr": 50.0
    },
    "Skarner": {
      "wr": 47.17,
      "pr": 0.14,
      "br": 0.17,
      "avgWr": 50.0
    },
    "Sona": {
      "wr": 52.17,
      "pr": 3.6,
      "br": 0.42,
      "avgWr": 50.0
    },
    "Soraka": {
      "wr": 51.87,
      "pr": 4.69,
      "br": 2.48,
      "avgWr": 50.0
    },
    "Swain": {
      "wr": 49.41,
      "pr": 4.5,
      "br": 5.83,
      "avgWr": 50.0
    },
    "Syndra": {
      "wr": 48.07,
      "pr": 0.1,
      "br": 2.27,
      "avgWr": 50.0
    },
    "Sylas": {
      "wr": 48.57,
      "pr": 0.84,
      "br": 11.12,
      "avgWr": 50.0
    },
    "Tahm Kench": {
      "wr": 49.71,
      "pr": 3.43,
      "br": 4.4,
      "avgWr": 50.0
    },
    "Taliyah": {
      "wr": 47.19,
      "pr": 0.08,
      "br": 0.19,
      "avgWr": 50.0
    },
    "Taric": {
      "wr": 52.47,
      "pr": 1.17,
      "br": 0.3,
      "avgWr": 50.0
    },
    "Thresh": {
      "wr": 50.52,
      "pr": 10.94,
      "br": 5.15,
      "avgWr": 50.0
    },
    "Teemo": {
      "wr": 51.37,
      "pr": 1.07,
      "br": 13.01,
      "avgWr": 50.0
    },
    "Trundle": {
      "wr": 46.78,
      "pr": 0.1,
      "br": 0.7,
      "avgWr": 50.0
    },
    "Tristana": {
      "wr": 34.05,
      "pr": 0.03,
      "br": 2.38,
      "avgWr": 50.0
    },
    "Tryndamere": {
      "wr": 41.08,
      "pr": 0.02,
      "br": 2.78,
      "avgWr": 50.0
    },
    "Twisted Fate": {
      "wr": 47.75,
      "pr": 0.14,
      "br": 0.53,
      "avgWr": 50.0
    },
    "Udyr": {
      "wr": 42.8,
      "pr": 0.02,
      "br": 0.65,
      "avgWr": 50.0
    },
    "Twitch": {
      "wr": 42.47,
      "pr": 0.35,
      "br": 7.76,
      "avgWr": 50.0
    },
    "Urgot": {
      "wr": 43.85,
      "pr": 0.03,
      "br": 1.46,
      "avgWr": 50.0
    },
    "Varus": {
      "wr": 40.81,
      "pr": 0.09,
      "br": 2.51,
      "avgWr": 50.0
    },
    "Veigar": {
      "wr": 48.15,
      "pr": 0.73,
      "br": 4.05,
      "avgWr": 50.0
    },
    "Vel'Koz": {
      "wr": 51.03,
      "pr": 3.15,
      "br": 1.61,
      "avgWr": 50.0
    },
    "Vex": {
      "wr": 46.63,
      "pr": 0.11,
      "br": 4.19,
      "avgWr": 50.0
    },
    "Vi": {
      "wr": 46.18,
      "pr": 0.09,
      "br": 1.17,
      "avgWr": 50.0
    },
    "Viktor": {
      "wr": 46.17,
      "pr": 0.04,
      "br": 2.98,
      "avgWr": 50.0
    },
    "Volibear": {
      "wr": 41.7,
      "pr": 0.05,
      "br": 3.88,
      "avgWr": 50.0
    },
    "Xerath": {
      "wr": 50.78,
      "pr": 4.11,
      "br": 10.64,
      "avgWr": 50.0
    },
    "Xin Zhao": {
      "wr": 46.2,
      "pr": 0.07,
      "br": 2.65,
      "avgWr": 50.0
    },
    "Yasuo": {
      "wr": 41.48,
      "pr": 0.1,
      "br": 20.71,
      "avgWr": 50.0
    },
    "Yorick": {
      "wr": 44.43,
      "pr": 0.05,
      "br": 12.52,
      "avgWr": 50.0
    },
    "Yuumi": {
      "wr": 47.77,
      "pr": 4.69,
      "br": 4.38,
      "avgWr": 50.0
    },
    "Zaahen": {
      "wr": 44.18,
      "pr": 0.03,
      "br": 4.15,
      "avgWr": 50.0
    },
    "Zed": {
      "wr": 44.33,
      "pr": 0.09,
      "br": 22.89,
      "avgWr": 50.0
    },
    "Zac": {
      "wr": 48.63,
      "pr": 0.24,
      "br": 0.77,
      "avgWr": 50.0
    },
    "Ziggs": {
      "wr": 48.19,
      "pr": 0.33,
      "br": 0.76,
      "avgWr": 50.0
    },
    "Zilean": {
      "wr": 51.77,
      "pr": 1.97,
      "br": 0.8,
      "avgWr": 50.0
    },
    "Zoe": {
      "wr": 48.3,
      "pr": 0.62,
      "br": 3.48,
      "avgWr": 50.0
    },
    "Zyra": {
      "wr": 51.4,
      "pr": 4.07,
      "br": 4.19,
      "avgWr": 50.0
    }
  }
}